broccolimd/__init__.py
broccolimd/main.py
broccolimd-0.2.0.dist-info/METADATA
broccolimd-0.2.0.dist-info/WHEEL
broccolimd-0.2.0.dist-info/entry_points.txt
broccolimd-0.2.0.dist-info/licenses/LICENSE.txt
broccolimd-0.2.0.dist-info/RECORD
